{
    "keep": {
        "days": true,
        "amount": 30
    },
    "auditLog": "logs/.8a4947b059085db6b703088a89d27d72eb65a1e6-audit.json",
    "files": [
        {
            "date": 1762809911278,
            "name": "logs/queries-error-2025-11-10.log",
            "hash": "54cccad687bba0f6183472c968ede5195a4f858629ff144f46f3454c4c5d3857"
        },
        {
            "date": 1763046548469,
            "name": "logs/queries-error-2025-11-13.log",
            "hash": "f3f782e024516846a5c74649084844e1acccdaec96eb68deded6d8ebd99262ea"
        }
    ],
    "hashType": "sha256"
}